[
    {
        "url": "http://farm4.staticflickr.com/3619/5846608500_23b20c8493_b.jpg", 
        "title": "Silence speaks louder than words", 
        "size": {
            "h": 1024, 
            "w": 1024
        }
    }, 
    {
        "url": "http://farm6.staticflickr.com/5235/5829132492_eae1f0062a_b.jpg", 
        "title": "Where am I ?", 
        "size": {
            "h": 1024, 
            "w": 1024
        }
    }, 
    {
        "url": "http://farm4.staticflickr.com/3287/5794116747_386b449f15_b.jpg", 
        "title": "Outside world", 
        "size": {
            "h": 686, 
            "w": 1024
        }
    }, 
    {
        "url": "http://farm3.staticflickr.com/2537/5786280611_803b3d548c_b.jpg", 
        "title": "Vague Dream", 
        "size": {
            "h": 686, 
            "w": 1024
        }
    }, 
    {
        "url": "http://farm4.staticflickr.com/3657/5719497148_ac8fced49b_b.jpg", 
        "title": "Edgy Truth...", 
        "size": {
            "h": 686, 
            "w": 1024
        }
    }, 
    {
        "url": "http://farm3.staticflickr.com/2712/5718467838_d8e92bee65_b.jpg", 
        "title": "Spooned", 
        "size": {
            "h": 1024, 
            "w": 686
        }
    }, 
    {
        "url": "http://farm6.staticflickr.com/5182/5698401507_e6a9d3240b_b.jpg", 
        "title": "Just chill", 
        "size": {
            "h": 686, 
            "w": 1024
        }
    }, 
    {
        "url": "http://farm3.staticflickr.com/2679/5698378279_84bb5ed294_b.jpg", 
        "title": "Just chill", 
        "size": {
            "h": 686, 
            "w": 1024
        }
    }, 
    {
        "url": "http://farm3.staticflickr.com/2463/5694186615_7cefc94d08_b.jpg", 
        "title": "droplets", 
        "size": {
            "h": 686, 
            "w": 1024
        }
    }, 
    {
        "url": "http://farm3.staticflickr.com/2186/5694186295_a7907eb63a_b.jpg", 
        "title": "Microtime", 
        "size": {
            "h": 686, 
            "w": 1024
        }
    }, 
    {
        "url": "http://farm6.staticflickr.com/5142/5624381634_d383f66c20_b.jpg", 
        "title": "Stack-overflow", 
        "size": {
            "h": 1024, 
            "w": 657
        }
    }, 
    {
        "url": "http://farm6.staticflickr.com/5105/5605908527_b877a6cde9_b.jpg", 
        "title": "Number 4. Privet Drive.", 
        "size": {
            "h": 1014, 
            "w": 1024
        }
    }, 
    {
        "url": "http://farm5.staticflickr.com/4097/5602242923_f43dea24c6_b.jpg", 
        "title": "Tick tock", 
        "size": {
            "h": 686, 
            "w": 1024
        }
    }, 
    {
        "url": "http://farm6.staticflickr.com/5135/5525500551_1475716619_b.jpg", 
        "title": "Wall Art", 
        "size": {
            "h": 1024, 
            "w": 686
        }
    }, 
    {
        "url": "http://farm6.staticflickr.com/5292/5475487437_c12575ef05_b.jpg", 
        "title": "Night view of bangalore", 
        "size": {
            "h": 685, 
            "w": 1024
        }
    }, 
    {
        "url": "http://farm6.staticflickr.com/5099/5458331168_7c0f9f2a72_b.jpg", 
        "title": "V.V.S Laxman", 
        "size": {
            "h": 1024, 
            "w": 742
        }
    }, 
    {
        "url": "http://farm6.staticflickr.com/5219/5458325252_b8290d8074_b.jpg", 
        "title": "Half what?", 
        "size": {
            "h": 685, 
            "w": 1024
        }
    }, 
    {
        "url": "http://farm6.staticflickr.com/5214/5433470761_3bd714e720_b.jpg", 
        "title": "de-Fence", 
        "size": {
            "h": 685, 
            "w": 1024
        }
    }, 
    {
        "url": "http://farm6.staticflickr.com/5167/5380560482_4ea8ca817b_b.jpg", 
        "title": "Oh dear heart...", 
        "size": {
            "h": 686, 
            "w": 1024
        }
    }, 
    {
        "url": "http://farm6.staticflickr.com/5244/5358794133_75007cfe94_b.jpg", 
        "title": "Boo, yes, that is me !", 
        "size": {
            "h": 686, 
            "w": 1024
        }
    }
]